audiofeatures/__init__.py
audiofeatures/features.py
audiofeatures-0.1.6.dist-info/METADATA
audiofeatures-0.1.6.dist-info/WHEEL
audiofeatures-0.1.6.dist-info/top_level.txt
audiofeatures-0.1.6.dist-info/RECORD
