Metadata-Version: 2.1
Name: audiofeatures
Version: 0.1.6
Summary: Extract MFCC, spectral, and pitch features from audio files
Requires-Dist: librosa
Requires-Dist: numpy
Requires-Dist: pandas
Requires-Dist: soundfile
